[

{
	"status": "start-template",
	"mode": "melon",
	"range": "medium",
	"day": 1,
	"port": "foggyValve",
	"duration": 5
},
{
	"status": "set-day",
	"day": 26
},
{
	"status": "on",
	"port": 23,
	"duration": 5
}
,
{
	"status": "on",
	"port": 22,
	"duration": 5
},
{
	"status": "on",
	"port": 19,
	"duration": 53
},
{
	"status": "on",
	"port": 18,
	"duration": 5
},
{
	"status": "on",
	"port": 5,
	"duration": 5
},
{
	"status": "on",
	"port": 17,
	"duration": 5
},
{
	"status": "on",
	"port": 17,
	"duration": 5
}


]

